data2latex/__init__.py
data2latex/dm.py
data2latex/environments.py
data2latex/features.py
data2latex/iter_protocols.py
data2latex/plot.py
data2latex/table.py
data2latex-1.0.5.dist-info/LICENSE
data2latex-1.0.5.dist-info/METADATA
data2latex-1.0.5.dist-info/WHEEL
data2latex-1.0.5.dist-info/top_level.txt
data2latex-1.0.5.dist-info/RECORD
