Metadata-Version: 2.1
Name: data2latex
Version: 1.0.5
Summary: Package prototype for simple generation of LaTeX tables and plots from scientific data for use in any document.
Author-email: Richard Kokštein <richard.Kokstein@fs.cvut.cz>
License: MIT License
Project-URL: Homepage, https://github.com/Trolobezka/data2latex
Project-URL: Repository, https://github.com/Trolobezka/data2latex
Project-URL: Documentation, https://trolobezka.github.io/data2latex-docs
Project-URL: Bug Tracker, https://github.com/Trolobezka/data2latex/issues
Keywords: generation,latex,table,plot,graph,array,datatable
Classifier: Programming Language :: Python :: 3
Classifier: Development Status :: 4 - Beta
Classifier: License :: OSI Approved :: MIT License
Classifier: Operating System :: OS Independent
Classifier: Natural Language :: English
Classifier: Intended Audience :: Science/Research
Classifier: Topic :: Utilities
Classifier: Topic :: Scientific/Engineering
Classifier: Topic :: Scientific/Engineering :: Visualization
Requires-Python: >=3.10
License-File: LICENSE
Requires-Dist: pylatex (>=1.4.1)
Provides-Extra: dev
Requires-Dist: matplotlib (>=3.7.1) ; extra == 'dev'
Requires-Dist: numpy (>=1.24.3) ; extra == 'dev'
Requires-Dist: pandas (>=2.0.1) ; extra == 'dev'
Requires-Dist: black (>=22.10.0) ; extra == 'dev'
Requires-Dist: sphinx (>=6.2.1) ; extra == 'dev'
Requires-Dist: sphinx-rtd-theme (>=1.2.0) ; extra == 'dev'
Requires-Dist: build (>=0.10.0) ; extra == 'dev'
Requires-Dist: twine (>=4.0.2) ; extra == 'dev'
Requires-Dist: pytest (>=7.3.1) ; extra == 'dev'
